covidTTI/__init__.py
covidTTI/analysis.py
covidTTI/cases.py
covidTTI/contacts.py
covidTTI/model.py
covidTTI/outputs.py
covidTTI/sim.py
covidTTI/utils.py
covidTTI-0.1.6.dist-info/METADATA
covidTTI-0.1.6.dist-info/WHEEL
covidTTI-0.1.6.dist-info/top_level.txt
covidTTI-0.1.6.dist-info/RECORD
